change_event_service/__init__.py
change_event_service/config.py
change_event_service/main.py
change_event_service/database/__init__.py
change_event_service/modules/__init__.py
change_event_service/modules/job/__init__.py
change_event_service/modules/job/utils.py
change_event_service/modules/rest/__init__.py
change_event_service/modules/rest/business.py
change_event_service/modules/rest/errors.py
change_event_service/modules/rest/models.py
change_event_service/modules/rest/schemas.py
change_event_service/modules/rest/utils.py
change_event_service/modules/rest/views.py
change_event_service/utils/__init__.py
change_event_service/utils/settings.py
change_event_service-3.0.3.data/scripts/change-event-service
change_event_service-3.0.3.dist-info/METADATA
change_event_service-3.0.3.dist-info/WHEEL
change_event_service-3.0.3.dist-info/top_level.txt
change_event_service-3.0.3.dist-info/RECORD
