Metadata-Version: 2.1
Name: change-event-service
Version: 3.0.3
Summary: Change Event Service
Home-page: https://github.com/mantis-software-company/change-event-service
Author: Ramazan Çetin
Author-email: lramazancetinl@gmail.com
Platform: all
Classifier: License :: OSI Approved :: Apache Software License
Classifier: Topic :: Internet
Classifier: Topic :: Software Development
Classifier: Topic :: Utilities
Classifier: Intended Audience :: Developers
Classifier: Operating System :: MacOS
Classifier: Operating System :: POSIX
Classifier: Operating System :: Microsoft
Classifier: Programming Language :: Python
Classifier: Programming Language :: Python :: 3
Classifier: Programming Language :: Python :: 3.8
Requires-Dist: SQLAlchemy ==1.4.29
Requires-Dist: Flask ~=2.0.2
Requires-Dist: flask-smorest ~=0.36.0
Requires-Dist: marshmallow ~=3.14.1
Requires-Dist: pyctuator ~=0.18.1
Requires-Dist: Flask-SQLAlchemy ==2.5.1
Requires-Dist: SQLAlchemy-Utils ~=0.38.2
Requires-Dist: psycopg2-binary ~=2.9.3
Requires-Dist: retry ~=0.9.2
Requires-Dist: Flask-APScheduler ==1.12.3
Requires-Dist: pika ~=1.2.0
Requires-Dist: python-slugify ~=5.0.2
Requires-Dist: requests ~=2.27.1
